KerasModelManager/ModelManager.py
KerasModelManager/__init__.py
KerasModelManager/utils.py
KerasModelManager-0.0.10.dist-info/LICENSE
KerasModelManager-0.0.10.dist-info/METADATA
KerasModelManager-0.0.10.dist-info/WHEEL
KerasModelManager-0.0.10.dist-info/top_level.txt
KerasModelManager-0.0.10.dist-info/RECORD
