Metadata-Version: 2.1
Name: KerasModelManager
Version: 0.0.10
Summary: A wrapper for Keras models
Home-page: https://github.com/daniel-men/ModelManager
Author: Daniel Mensing
Author-email: daniel.mensing@gmx.net
License: UNKNOWN
Download-URL: https://github.com/daniel-men/ModelManager/archive/0.0.6.tar.gz
Platform: UNKNOWN
Classifier: Programming Language :: Python :: 3
Classifier: License :: OSI Approved :: MIT License
Classifier: Operating System :: OS Independent
Requires-Python: >=3.6
License-File: LICENSE
Requires-Dist: numpy
Requires-Dist: dill
Requires-Dist: tensorflow
Requires-Dist: python-utility-functions
